keras_attention_block/__init__.py
keras_attention_block/attention.py
keras_attention_block/key_value_attention.py
keras_attention_block/key_value_attention3d.py
keras_attention_block/mixins.py
keras_attention_block/mulithead_attention.py
keras_attention_block/self_attention.py
keras_attention_block-0.0.2.data/data/requirements/requirements.txt
keras_attention_block-0.0.2.data/data/requirements/requirements_dev.txt
keras_attention_block-0.0.2.data/data/requirements/requirements_test.txt
keras_attention_block-0.0.2.dist-info/DESCRIPTION.rst
keras_attention_block-0.0.2.dist-info/METADATA
keras_attention_block-0.0.2.dist-info/RECORD
keras_attention_block-0.0.2.dist-info/WHEEL
keras_attention_block-0.0.2.dist-info/metadata.json
keras_attention_block-0.0.2.dist-info/top_level.txt
