Metadata-Version: 2.0
Name: keras-attention-block
Version: 0.0.2
Summary: simple tools
Home-page: https://github.com/NLP-Deeplearning-Club/keras_attention_block/
Author: hsz
Author-email: hsz1273327@gmail.com
License: MIT
Requires-Dist: mkl
Requires-Dist: numpy
Requires-Dist: scipy
Requires-Dist: scikit-learn
Requires-Dist: keras
Provides-Extra: dev
Requires-Dist: wheel; extra == 'dev'
Provides-Extra: test
Requires-Dist: coverage; extra == 'test'
Requires-Dist: mypy; extra == 'test'
Requires-Dist: mypy-extensions; extra == 'test'
Requires-Dist: lxml; extra == 'test'
